{
	"name": "LS_AZSQL_ANNE",
	"properties": {
		"parameters": {
			"ScrectName": {
				"type": "string"
			}
		},
		"annotations": [],
		"type": "AzureSqlDatabase",
		"typeProperties": {
			"connectionString": {
				"type": "AzureKeyVaultSecret",
				"store": {
					"referenceName": "AZK01_ANNE",
					"type": "LinkedServiceReference"
				},
				"secretName": {
					"value": "@linkedService().ScrectName",
					"type": "Expression"
				}
			}
		}
	},
	"type": "Microsoft.DataFactory/factories/linkedservices"
}